editty/__init__.py
editty/editty.py
editty/program.py
editty/segment.py
editty/source.py
editty-0.0.1.dist-info/AUTHORS
editty-0.0.1.dist-info/METADATA
editty-0.0.1.dist-info/WHEEL
editty-0.0.1.dist-info/entry_points.txt
editty-0.0.1.dist-info/pbr.json
editty-0.0.1.dist-info/top_level.txt
editty-0.0.1.dist-info/RECORD
