Metadata-Version: 2.1
Name: editty
Version: 0.0.1
Summary: Terminal-based non-linear editor for terminal recordings
Home-page: UNKNOWN
Author: James E. Blair
Author-email: corvus@gnu.org
License: UNKNOWN
Platform: UNKNOWN
Classifier: Environment :: Console
Classifier: Intended Audience :: Developers
Classifier: Intended Audience :: Education
Classifier: Intended Audience :: End Users/Desktop
Classifier: Intended Audience :: Information Technology
Classifier: Intended Audience :: System Administrators
Classifier: License :: OSI Approved :: GNU General Public License v3 or later (GPLv3+)
Classifier: Programming Language :: Python
Classifier: Topic :: Multimedia :: Graphics :: Presentation
Requires-Dist: pbr (>=1.0.0)
Requires-Dist: urwid
